gmail_scanner
